LICENSE
README.md
setup.py
django_atomic_migrations/__init__.py
django_atomic_migrations.egg-info/PKG-INFO
django_atomic_migrations.egg-info/SOURCES.txt
django_atomic_migrations.egg-info/dependency_links.txt
django_atomic_migrations.egg-info/top_level.txt
django_atomic_migrations/management/__init__.py
django_atomic_migrations/management/commands/__init__.py
django_atomic_migrations/management/commands/add-migrations-constraint.py