Metadata-Version: 2.1
Name: django-atomic-migrations
Version: 0.2.0
Summary: Adds unique constraint on Django's migration tracking model
Home-page: https://github.com/rkojedzinszky/django-atomic-migrations
Author: Richard Kojedzinszky
Author-email: richard@kojedz.in
Classifier: Programming Language :: Python :: 3
Classifier: License :: OSI Approved :: MIT License
Classifier: Operating System :: OS Independent
Requires-Python: >=3.6
License-File: LICENSE
